LICENSE
README.md
setup.py
NlpToolkit_ParseTree_Cy.egg-info/PKG-INFO
NlpToolkit_ParseTree_Cy.egg-info/SOURCES.txt
NlpToolkit_ParseTree_Cy.egg-info/dependency_links.txt
NlpToolkit_ParseTree_Cy.egg-info/requires.txt
NlpToolkit_ParseTree_Cy.egg-info/top_level.txt
ParseTree/ConstituentSpan.c
ParseTree/ConstituentSpan.pxd
ParseTree/ConstituentSpan.pyx
ParseTree/NodeCollector.c
ParseTree/NodeCollector.pxd
ParseTree/NodeCollector.pyx
ParseTree/ParallelTreeBank.c
ParseTree/ParallelTreeBank.pxd
ParseTree/ParallelTreeBank.pyx
ParseTree/ParseNode.c
ParseTree/ParseNode.pxd
ParseTree/ParseNode.pyx
ParseTree/ParseTree.c
ParseTree/ParseTree.pxd
ParseTree/ParseTree.pyx
ParseTree/SearchDirectionType.py
ParseTree/Symbol.c
ParseTree/Symbol.pxd
ParseTree/Symbol.pyx
ParseTree/TreeBank.c
ParseTree/TreeBank.pxd
ParseTree/TreeBank.pyx
ParseTree/__init__.py
ParseTree/NodeCondition/IsEnglishLeaf.c
ParseTree/NodeCondition/IsEnglishLeaf.pxd
ParseTree/NodeCondition/IsEnglishLeaf.pyx
ParseTree/NodeCondition/IsLeaf.c
ParseTree/NodeCondition/IsLeaf.pxd
ParseTree/NodeCondition/IsLeaf.pyx
ParseTree/NodeCondition/NodeCondition.c
ParseTree/NodeCondition/NodeCondition.pxd
ParseTree/NodeCondition/NodeCondition.pyx
ParseTree/NodeCondition/__init__.py
nlptoolkit_parsetree_cy.egg-info/PKG-INFO
nlptoolkit_parsetree_cy.egg-info/SOURCES.txt
nlptoolkit_parsetree_cy.egg-info/dependency_links.txt
nlptoolkit_parsetree_cy.egg-info/requires.txt
nlptoolkit_parsetree_cy.egg-info/top_level.txt