Metadata-Version: 2.4
Name: nlptoolkit-parsetree-cy
Version: 1.0.11
Summary: Constituency Parse Tree Library
Home-page: https://github.com/StarlangSoftware/ParseTree-Cy
Author: olcaytaner
Author-email: olcay.yildiz@ozyegin.edu.tr
License-File: LICENSE
Requires-Dist: NlpToolkit-Dictionary-Cy
Dynamic: author
Dynamic: author-email
Dynamic: description
Dynamic: description-content-type
Dynamic: home-page
Dynamic: license-file
Dynamic: requires-dist
Dynamic: summary
